[{"id":1,"name":"Energy Equipment & Services","industryGroupId":1},{"id":2,"name":"Oil, Gas & Consumable Fuels","industryGroupId":1},{"id":3,"name":"Chemicals","industryGroupId":2},{"id":4,"name":"Construction Materials","industryGroupId":2},{"id":5,"name":"Containers & Packaging","industryGroupId":2},{"id":6,"name":"Metals & Mining","industryGroupId":2},{"id":7,"name":"Paper & Forest Products","industryGroupId":2},{"id":8,"name":"Aerospace & Defense","industryGroupId":3},{"id":9,"name":"Building Products","industryGroupId":3},{"id":10,"name":"Construction & Engineering","industryGroupId":3},{"id":11,"name":"Electrical Equipment","industryGroupId":3},{"id":12,"name":"Industrial Conglomerates","industryGroupId":3},{"id":13,"name":"Machinery","industryGroupId":3},{"id":14,"name":"Trading Companies & Distributors","industryGroupId":3},{"id":15,"name":"Commercial Services & Supplies","industryGroupId":4},{"id":16,"name":"Professional Services","industryGroupId":4},{"id":17,"name":"Air Freight & Logistics","industryGroupId":5},{"id":18,"name":"Passenger Airlines (New name)","industryGroupId":5},{"id":19,"name":"Marine Transportation (New Name)","industryGroupId":5},{"id":20,"name":"Ground Transportation (New Name)","industryGroupId":5},{"id":21,"name":"Transportation Infrastructure","industryGroupId":5},{"id":22,"name":"Automobile Components (New Name)","industryGroupId":6},{"id":23,"name":"Automobiles","industryGroupId":6},{"id":24,"name":"Household Durables","industryGroupId":7},{"id":25,"name":"Leisure Products","industryGroupId":7},{"id":26,"name":"Textiles, Apparel & Luxury Goods","industryGroupId":7},{"id":27,"name":"Hotels, Restaurants & Leisure","industryGroupId":8},{"id":28,"name":"Diversified Consumer Services","industryGroupId":8},{"id":29,"name":"Distributors","industryGroupId":9},{"id":30,"name":"Internet & Direct Marketing Retail (Discontinued)","industryGroupId":9},{"id":31,"name":"Broadline Retail (New Name)","industryGroupId":9},{"id":32,"name":"Specialty Retail","industryGroupId":9},{"id":33,"name":"Consumer Staples Distribution & Retail (New Name)","industryGroupId":10},{"id":34,"name":"Beverages","industryGroupId":11},{"id":35,"name":"Food Products","industryGroupId":11},{"id":36,"name":"Tobacco","industryGroupId":11},{"id":37,"name":"Household Products","industryGroupId":12},{"id":38,"name":"Personal Care Products (New Name)","industryGroupId":12},{"id":39,"name":"Health Care Equipment & Supplies","industryGroupId":13},{"id":40,"name":"Health Care Providers & Services","industryGroupId":13},{"id":41,"name":"Health Care Technology","industryGroupId":13},{"id":42,"name":"Biotechnology","industryGroupId":14},{"id":43,"name":"Pharmaceuticals","industryGroupId":14},{"id":44,"name":"Life Sciences Tools & Services","industryGroupId":14},{"id":45,"name":"Banks","industryGroupId":15},{"id":46,"name":"Thrifts & Mortgage Finance (Discontinued)","industryGroupId":15},{"id":47,"name":" Financial Services (New Name)","industryGroupId":16},{"id":48,"name":"Consumer Finance","industryGroupId":16},{"id":49,"name":"Capital Markets","industryGroupId":16},{"id":50,"name":"Mortgage Real Estate Investment\r\nTrusts (REITs)","industryGroupId":16},{"id":51,"name":"Insurance","industryGroupId":17},{"id":52,"name":"IT Services","industryGroupId":18},{"id":53,"name":"Software","industryGroupId":18},{"id":54,"name":"Communications Equipment","industryGroupId":19},{"id":55,"name":"Technology Hardware, Storage & Peripherals","industryGroupId":19},{"id":56,"name":"Electronic Equipment, Instruments & Components","industryGroupId":19},{"id":57,"name":"Semiconductors & Semiconductor Equipment","industryGroupId":20},{"id":58,"name":"Diversified Telecommunication Services","industryGroupId":21},{"id":59,"name":"Wireless Telecommunication Services","industryGroupId":21},{"id":60,"name":"Media","industryGroupId":22},{"id":61,"name":"Entertainment","industryGroupId":22},{"id":62,"name":"Interactive Media & Services","industryGroupId":22},{"id":63,"name":"Electric Utilities","industryGroupId":23},{"id":64,"name":"Gas Utilities","industryGroupId":23},{"id":65,"name":"Multi-Utilities","industryGroupId":23},{"id":66,"name":"Water Utilities","industryGroupId":23},{"id":67,"name":"Independent Power and Renewable Electricity Producers","industryGroupId":23},{"id":68,"name":"Diversified REITs (New Name)","industryGroupId":24},{"id":69,"name":"Industrial REITs (New)","industryGroupId":24},{"id":70,"name":"Hotel & Resort REITs (New)","industryGroupId":24},{"id":71,"name":"Office REITs (New)","industryGroupId":24},{"id":72,"name":"Health Care REITs (New)","industryGroupId":24},{"id":73,"name":"Residential REITs (New)","industryGroupId":24},{"id":74,"name":"Retail REITs (New)","industryGroupId":24},{"id":75,"name":"Specialized REITs (New)","industryGroupId":24},{"id":76,"name":"Real Estate Management & Development (New Code)","industryGroupId":25}]